README
ez_setup.py
setup.cfg
setup.py
version.info
bin/cvsci
bin/dbsh
dbsh.egg-info/PKG-INFO
dbsh.egg-info/SOURCES.txt
dbsh.egg-info/dependency_links.txt
dbsh.egg-info/not-zip-safe
dbsh.egg-info/requires.txt
dbsh.egg-info/top_level.txt
doc/LICENSE
doc/TODO
src/__init__.py
src/config/ipythonrc
src/dbsh/__init__.py
src/dbsh/dbcmd.py
src/dbsh/dbdot.py
src/dbsh/dbprint.py
src/dbsh/dbshell.py
src/dbsh/ipy_profile_dbsh.py
src/dbsh/ipy_user_conf.py
src/dbsh/utils.py