Metadata-Version: 1.0
Name: dbsh
Version: 0.1.6
Summary: Common, interactive, programmable environment and simple shell to connect and manipulate your favorite DB content
Home-page: http://www.dbshell.org
Author: Valentin Kuznetsov
Author-email: dbsh4u@gmail.com
License: BSD License
Platform: UNKNOWN
Classifier: Environment :: Console
Classifier: Intended Audience :: Developers
Classifier: Intended Audience :: End Users/Desktop
Classifier: Intended Audience :: System Administrators
Classifier: License :: OSI Approved :: BSD License
Classifier: Operating System :: MacOS :: MacOS X
Classifier: Operating System :: Microsoft :: Windows
Classifier: Operating System :: POSIX
Classifier: Programming Language :: Python
Classifier: Topic :: Database :: Front-Ends
